surfinBH/__init__.py
surfinBH/_dataPath.py
surfinBH/_lal_spin_evolution.py
surfinBH/_loadFits.py
surfinBH/_utils.py
surfinBH/surfinBH.py
surfinBH/_eval_pysur/__init__.py
surfinBH/_eval_pysur/evaluate_fit.py
surfinBH/_fit_evaluators/__init__.py
surfinBH/_fit_evaluators/fit_3dq8.py
surfinBH/_fit_evaluators/fit_3dq8BMS.py
surfinBH/_fit_evaluators/fit_3dq8_RD.py
surfinBH/_fit_evaluators/fit_7dq2.py
surfinBH/_fit_evaluators/fit_7dq4.py
surfinBH/_fit_evaluators/fit_7dq4Emri.py
surfinBH/data/README
surfinBH/data/fit_3dq8.h5
surfinBH/data/fit_7dq2.h5
surfinBH-1.2.6.dist-info/LICENSE
surfinBH-1.2.6.dist-info/METADATA
surfinBH-1.2.6.dist-info/WHEEL
surfinBH-1.2.6.dist-info/pbr.json
surfinBH-1.2.6.dist-info/top_level.txt
surfinBH-1.2.6.dist-info/RECORD
