Metadata-Version: 2.1
Name: surfinBH
Version: 1.2.6
Summary: Surrogate Final BH properties.
Home-page: https://github.com/vijayvarma392/surfinBH
Author: Vijay Varma
Author-email: vvarma@caltech.edu
Keywords: black-holes gravitational-waves Gaussian-process-regression
Classifier: Intended Audience :: Science/Research
Classifier: Natural Language :: English
Classifier: Topic :: Scientific/Engineering :: Physics
Classifier: Topic :: Scientific/Engineering :: Astronomy
Classifier: License :: OSI Approved :: MIT License
Classifier: Programming Language :: Python
Classifier: Operating System :: OS Independent
License-File: LICENSE
Requires-Dist: numpy
Requires-Dist: scipy
Requires-Dist: h5py
Requires-Dist: scikit-learn >=0.19.1
Requires-Dist: lalsuite >=6.70
Requires-Dist: gwsurrogate
